pinax/__init__.py
pinax/submissions/__init__.py
pinax/submissions/admin.py
pinax/submissions/compat.py
pinax/submissions/conf.py
pinax/submissions/forms.py
pinax/submissions/hooks.py
pinax/submissions/models.py
pinax/submissions/urls.py
pinax/submissions/utils.py
pinax/submissions/views.py
pinax/submissions/management/__init__.py
pinax/submissions/management/commands/__init__.py
pinax/submissions/management/commands/assign_reviewers.py
pinax/submissions/management/commands/create_review_permissions.py
pinax/submissions/migrations/0001_initial.py
pinax/submissions/migrations/__init__.py
pinax/submissions/tests/__init__.py
pinax/submissions/tests/tests.py
pinax/submissions/tests/urls.py
pinax_submissions-2.0.0.dist-info/AUTHORS
pinax_submissions-2.0.0.dist-info/LICENSE
pinax_submissions-2.0.0.dist-info/METADATA
pinax_submissions-2.0.0.dist-info/WHEEL
pinax_submissions-2.0.0.dist-info/top_level.txt
pinax_submissions-2.0.0.dist-info/RECORD
