Metadata-Version: 2.1
Name: pinax-submissions
Version: 2.0.0
Summary: a Django app for proposing and reviewing submissions
Home-page: http://github.com/pinax/pinax-submissions/
Author: Pinax Team
Author-email: team@pinaxproject.com
License: MIT
Platform: UNKNOWN
Classifier: Development Status :: 5 - Production/Stable
Classifier: Environment :: Web Environment
Classifier: Framework :: Django
Classifier: Framework :: Django :: 2.2
Classifier: Framework :: Django :: 3.0
Classifier: Intended Audience :: Developers
Classifier: License :: OSI Approved :: MIT License
Classifier: Operating System :: OS Independent
Classifier: Programming Language :: Python
Classifier: Programming Language :: Python :: 3.6
Classifier: Programming Language :: Python :: 3.7
Classifier: Programming Language :: Python :: 3.8
Classifier: Topic :: Software Development :: Libraries :: Python Modules
Requires-Dist: django (>=2.2)
Requires-Dist: Markdown (>=2.6.3)
Requires-Dist: django-model-utils (>=3.1.1)
Requires-Dist: django-appconf (>=1.0.2)
